bindiff/__init__.py
bindiff/__main__.py
bindiff/bindiff.py
bindiff/file.py
bindiff/types.py
python_bindiff-0.3.4.dist-info/licenses/LICENSE
python_bindiff-0.3.4.dist-info/METADATA
python_bindiff-0.3.4.dist-info/WHEEL
python_bindiff-0.3.4.dist-info/entry_points.txt
python_bindiff-0.3.4.dist-info/top_level.txt
python_bindiff-0.3.4.dist-info/RECORD
