Metadata-Version: 2.4
Name: python-bindiff
Version: 0.3.4
Summary: Python wrapper to manipulate bindiff files
Author-email: Robin David <rdavid@quarkslab.com>
License: Apache Software License (Apache License, Version 2)
Project-URL: Homepage, https://github.com/quarkslab/python-bindiff
Project-URL: Repository, https://github.com/quarkslab/python-bindiff
Project-URL: Documentation, https://diffing.quarkslab.com/differs/bindiff.html#python-bindiff
Project-URL: Bug Tracker, https://github.com/quarkslab/python-bindiff/issues
Classifier: Topic :: Security
Classifier: Environment :: Console
Classifier: Operating System :: OS Independent
Requires-Python: >=3.9
License-File: LICENSE
Requires-Dist: python-magic; os_name != "nt"
Requires-Dist: python-magic-bin; os_name == "nt"
Requires-Dist: click
Requires-Dist: python-binexport>=0.3.3
Dynamic: license-file
